<annotation>
	<folder>vn</folder>
	<filename>image_349.jpg</filename>
	<path>E:\VIRTUAL_SHARED_FOLDER\vn\image_349.jpg</path>
	<source>
		<database>Unknown</database>
	</source>
	<size>
		<width>325</width>
		<height>1006</height>
		<depth>3</depth>
	</size>
	<segmented>0</segmented>
	<object>
		<name>veg_nonveg</name>
		<pose>Unspecified</pose>
		<truncated>0</truncated>
		<difficult>0</difficult>
		<bndbox>
			<xmin>69</xmin>
			<ymin>734</ymin>
			<xmax>105</xmax>
			<ymax>769</ymax>
		</bndbox>
	</object>
</annotation>
